setup.py
app_musor/__init__.py
app_musor/module1.py
app_musor/module2.py
app_musor.egg-info/PKG-INFO
app_musor.egg-info/SOURCES.txt
app_musor.egg-info/dependency_links.txt
app_musor.egg-info/top_level.txt