Metadata-Version: 2.1
Name: app-musor
Version: 0.0.1
Summary: My Package
Author: Fedor
Author-email: zaprudnovfedor@gmail.com
